neon_phal_plugin_skill_api/__init__.py
neon_phal_plugin_skill_api/version.py
tests/__init__.py
tests/test_plugin.py
neon_phal_plugin_skill_api-0.0.1a1.dist-info/LICENSE.md
neon_phal_plugin_skill_api-0.0.1a1.dist-info/METADATA
neon_phal_plugin_skill_api-0.0.1a1.dist-info/WHEEL
neon_phal_plugin_skill_api-0.0.1a1.dist-info/entry_points.txt
neon_phal_plugin_skill_api-0.0.1a1.dist-info/top_level.txt
neon_phal_plugin_skill_api-0.0.1a1.dist-info/RECORD
