Metadata-Version: 2.1
Name: neon-phal-plugin-skill-api
Version: 0.0.1a1
Summary: Plugin for accessing the Skill API
Home-page: https://github.com/NeonGeckoCom/neon-phal-plugin-skill-api
Author: Neongecko
Author-email: developers@neon.ai
License: BSD-3
License-File: LICENSE.md
Requires-Dist: ovos-utils>=0.0.26,~=0.0
Requires-Dist: ovos-plugin-manager>=0.0.20,~=0.0
Requires-Dist: ovos-bus-client>=0.0.3,~=0.0
Provides-Extra: test
Requires-Dist: pytest; extra == "test"
